starfish/REQUIREMENTS-STRICT.txt
starfish/__init__.py
starfish/__main__.py
starfish/config.py
starfish/data.py
starfish/image.py
starfish/morphology.py
starfish/spots.py
starfish/test.py
starfish/types.py
starfish/core/__init__.py
starfish/core/_display.py
starfish/core/_version.py
starfish/core/errors.py
starfish/core/starfish.py
starfish/core/codebook/__init__.py
starfish/core/codebook/_format.py
starfish/core/codebook/codebook.py
starfish/core/codebook/test/__init__.py
starfish/core/codebook/test/factories.py
starfish/core/codebook/test/test_approximate_nearest_code.py
starfish/core/codebook/test/test_code_length.py
starfish/core/codebook/test/test_from_code_array.py
starfish/core/codebook/test/test_metric_decode.py
starfish/core/codebook/test/test_normalize_code_traces.py
starfish/core/codebook/test/test_per_round_max_decode.py
starfish/core/codebook/test/test_synthetic_one_hot_codebook.py
starfish/core/codebook/test/test_to_json.py
starfish/core/config/__init__.py
starfish/core/config/test/__init__.py
starfish/core/config/test/test_config.py
starfish/core/experiment/__init__.py
starfish/core/experiment/experiment.py
starfish/core/experiment/version.py
starfish/core/experiment/builder/__init__.py
starfish/core/experiment/builder/builder.py
starfish/core/experiment/builder/defaultproviders.py
starfish/core/experiment/builder/inplace.py
starfish/core/experiment/builder/orderediterator.py
starfish/core/experiment/builder/providers.py
starfish/core/experiment/builder/structured_formatter.py
starfish/core/experiment/builder/test/__init__.py
starfish/core/experiment/builder/test/test_inplace.py
starfish/core/experiment/builder/test/test_orderediterator.py
starfish/core/experiment/builder/test/test_small_axis.py
starfish/core/experiment/builder/test/factories/__init__.py
starfish/core/experiment/builder/test/factories/all_purpose.py
starfish/core/experiment/builder/test/factories/unique_tiles.py
starfish/core/experiment/builder/test/structured_formatter/__init__.py
starfish-0.3.3.dist-info/licenses/LICENSE
starfish-0.3.3.dist-info/METADATA
starfish-0.3.3.dist-info/WHEEL
starfish-0.3.3.dist-info/entry_points.txt
starfish-0.3.3.dist-info/top_level.txt
starfish-0.3.3.dist-info/RECORD
