Metadata-Version: 2.4
Name: starfish
Version: 0.3.3
Summary: Pipelines and pipeline components for the analysis of image-based transcriptomics data
Author-email: Deep Ganguli <dganguli@chanzuckerberg.com>
Maintainer-email: Lior Shachaf <shachaflior@gmail.com>
Project-URL: Homepage, https://spacetx-starfish.readthedocs.io/en/latest/
Project-URL: Documentation, https://spacetx-starfish.readthedocs.io/en/latest/
Project-URL: Repository, https://github.com/spacetx/starfish
Project-URL: Bug Tracker, https://github.com/spacetx/starfish/issues
Keywords: single-cell,image-based,transcriptomics
Classifier: Development Status :: 4 - Beta
Classifier: Natural Language :: English
Classifier: Operating System :: POSIX :: Linux
Classifier: Operating System :: Unix
Classifier: Operating System :: MacOS :: MacOS X
Classifier: Operating System :: Microsoft :: Windows
Classifier: License :: OSI Approved :: MIT License
Classifier: Programming Language :: Python :: 3
Classifier: Programming Language :: Python :: 3.9
Classifier: Programming Language :: Python :: 3.10
Classifier: Programming Language :: Python :: 3.11
Classifier: Programming Language :: Python :: 3.12
Requires-Python: <3.13,>=3.9
License-File: LICENSE
Requires-Dist: click
Requires-Dist: docutils<0.20
Requires-Dist: h5py
Requires-Dist: jsonschema<4.18
Requires-Dist: matplotlib<3.8
Requires-Dist: numpy<2
Requires-Dist: read_roi
Requires-Dist: regional
Requires-Dist: scikit-image>0.22
Requires-Dist: scikit-learn
Requires-Dist: seaborn
Requires-Dist: semantic_version
Requires-Dist: showit
Requires-Dist: slicedimage
Requires-Dist: sympy
Requires-Dist: tqdm
Requires-Dist: trackpy
Requires-Dist: validators
Requires-Dist: xarray<2023.09
Provides-Extra: napari
Requires-Dist: napari[all]>=0.4.18; extra == "napari"
Dynamic: license-file
Dynamic: provides-extra
Dynamic: requires-dist
